buslib/__init__.py
buslib/example_objects/__init__.py
buslib/example_objects/account.py
buslib/example_objects/address.py
buslib/example_objects/benchmark.py
buslib/example_objects/building_data.py
buslib/example_objects/occupant_response.py
buslib/example_objects/partner.py
buslib/example_objects/question.py
buslib/example_objects/survey.py
buslib-1.10.0.dist-info/METADATA
buslib-1.10.0.dist-info/RECORD
buslib-1.10.0.dist-info/WHEEL
buslib-1.10.0.dist-info/top_level.txt
